FadeMaxSize/__init__.py
FadeMaxSize/findMax.py
tests/__init__.py
tests/test_find.py
FadeMaxSize-1.0.0.dist-info/LICENSE
FadeMaxSize-1.0.0.dist-info/METADATA
FadeMaxSize-1.0.0.dist-info/WHEEL
FadeMaxSize-1.0.0.dist-info/top_level.txt
FadeMaxSize-1.0.0.dist-info/RECORD
