Metadata-Version: 2.1
Name: FadeMaxSize
Version: 1.0.0
Summary: Search for file with maximum size
Home-page: https://github.com/whyfade/FadeMaxSize
Author: Petrov D.S.
Author-email: pvrple.drank.xvi@gmail.com
License: UNKNOWN
Platform: any
Requires-Python: >=3.7
